imeta/__init__.py
imeta/exceptions.py
imeta/schema.py
imeta/serializer.py
imeta/schema/1.0.json
imeta/schema/1.1.json
imeta-1.2.0.dist-info/METADATA
imeta-1.2.0.dist-info/WHEEL
imeta-1.2.0.dist-info/top_level.txt
imeta-1.2.0.dist-info/RECORD
