Metadata-Version: 2.1
Name: imeta
Version: 1.2.0
Summary: Standard for capturing metadata about an image on the web
Author-email: Matt Wisniewski <healthycrowd@mattw.life>
License: MIT
Project-URL: homepage, https://github.com/healthycrowd/imeta
Keywords: imeta,utility,image,metadata
Classifier: Development Status :: 5 - Production/Stable
Classifier: Intended Audience :: Developers
Classifier: License :: OSI Approved :: MIT License
Classifier: Operating System :: POSIX
Classifier: Programming Language :: Python
Classifier: Programming Language :: Python :: 3
Classifier: Programming Language :: Python :: 3.8
Classifier: Programming Language :: Python :: 3.9
Classifier: Programming Language :: Python :: 3.10
Classifier: Programming Language :: Python :: 3.11
Classifier: Topic :: Software Development :: Libraries :: Python Modules
Classifier: Topic :: Utilities
Requires-Python: >=3.8.0
Requires-Dist: jsonschema (~=4.0)
